Metadata-Version: 2.1
Name: cscipy
Version: 0.0.1
Summary: Some scipy functions rewritten in Cython
Home-page: https://github.com/fzyukio/cscipy
Author: ['Yukio Fukuzawa']
License: MIT
Keywords: scipy,cython,distance
Platform: UNKNOWN
